MANIFEST.in
README.md
setup.py
bootstrap/__init__.py
bootstrap/static/bootstrap/css/bootstrap-theme.css
bootstrap/static/bootstrap/css/bootstrap-theme.min.css
bootstrap/static/bootstrap/css/bootstrap.css
bootstrap/static/bootstrap/css/bootstrap.min.css
bootstrap/static/bootstrap/fonts/glyphicons-halflings-regular.eot
bootstrap/static/bootstrap/fonts/glyphicons-halflings-regular.svg
bootstrap/static/bootstrap/fonts/glyphicons-halflings-regular.ttf
bootstrap/static/bootstrap/fonts/glyphicons-halflings-regular.woff
bootstrap/static/bootstrap/js/affix.js
bootstrap/static/bootstrap/js/alert.js
bootstrap/static/bootstrap/js/bootstrap.js
bootstrap/static/bootstrap/js/bootstrap.min.js
bootstrap/static/bootstrap/js/button.js
bootstrap/static/bootstrap/js/carousel.js
bootstrap/static/bootstrap/js/collapse.js
bootstrap/static/bootstrap/js/dropdown.js
bootstrap/static/bootstrap/js/modal.js
bootstrap/static/bootstrap/js/popover.js
bootstrap/static/bootstrap/js/scrollspy.js
bootstrap/static/bootstrap/js/tab.js
bootstrap/static/bootstrap/js/tooltip.js
bootstrap/static/bootstrap/js/transition.js
bootstrap/static/bootstrap/less/alerts.less
bootstrap/static/bootstrap/less/badges.less
bootstrap/static/bootstrap/less/bootstrap.less
bootstrap/static/bootstrap/less/breadcrumbs.less
bootstrap/static/bootstrap/less/button-groups.less
bootstrap/static/bootstrap/less/buttons.less
bootstrap/static/bootstrap/less/carousel.less
bootstrap/static/bootstrap/less/close.less
bootstrap/static/bootstrap/less/code.less
bootstrap/static/bootstrap/less/component-animations.less
bootstrap/static/bootstrap/less/dropdowns.less
bootstrap/static/bootstrap/less/forms.less
bootstrap/static/bootstrap/less/glyphicons.less
bootstrap/static/bootstrap/less/grid.less
bootstrap/static/bootstrap/less/input-groups.less
bootstrap/static/bootstrap/less/jumbotron.less
bootstrap/static/bootstrap/less/labels.less
bootstrap/static/bootstrap/less/list-group.less
bootstrap/static/bootstrap/less/media.less
django_staticfiles_bootstrap.egg-info/PKG-INFO
django_staticfiles_bootstrap.egg-info/SOURCES.txt
django_staticfiles_bootstrap.egg-info/dependency_links.txt
django_staticfiles_bootstrap.egg-info/not-zip-safe
django_staticfiles_bootstrap.egg-info/top_level.txt