Metadata-Version: 1.1
Name: django-staticfiles-bootstrap
Version: 3.0.2
Summary: Twitter Bootstrap staticfiles for django
Home-page: http://github.com/apreche/django-staticfiles-bootstrap
Author: Scott Rubin
Author-email: apreche@frontrowcrew.com
License: MIT
Platform: UNKNOWN
Classifier: Development Status :: 5 - Production/Stable
Classifier: Environment :: Web Environment
Classifier: Framework :: Django
Classifier: Intended Audience :: Developers
Classifier: License :: OSI Approved :: MIT License
Classifier: Natural Language :: English
Classifier: Operating System :: OS Independent
Classifier: Programming Language :: Python
Classifier: Topic :: Internet :: WWW/HTTP
